exiftool/__init__.py
exiftool/constants.py
exiftool/exceptions.py
exiftool/exiftool.py
exiftool/experimental.py
exiftool/helper.py
PyExifTool-0.5.5.dist-info/COPYING.BSD
PyExifTool-0.5.5.dist-info/COPYING.GPL
PyExifTool-0.5.5.dist-info/LICENSE
PyExifTool-0.5.5.dist-info/METADATA
PyExifTool-0.5.5.dist-info/WHEEL
PyExifTool-0.5.5.dist-info/top_level.txt
PyExifTool-0.5.5.dist-info/RECORD
