Metadata-Version: 2.1
Name: PyExifTool
Version: 0.5.5
Summary: Python wrapper for exiftool
Home-page: http://github.com/sylikc/pyexiftool
Author: Kevin M (sylikc), Sven Marnach, various contributors
Author-email: sylikc@gmail.com
License: GPLv3+/BSD
Project-URL: Source, https://github.com/sylikc/pyexiftool
Project-URL: Tracker, https://github.com/sylikc/pyexiftool/issues
Project-URL: Changelog, https://github.com/sylikc/pyexiftool/blob/master/CHANGELOG.md
Project-URL: Documentation, https://sylikc.github.io/pyexiftool/
Keywords: exiftool image exif metadata photo video photography
Classifier: Development Status :: 4 - Beta
Classifier: Intended Audience :: Developers
Classifier: License :: OSI Approved :: BSD License
Classifier: License :: OSI Approved :: GNU General Public License v3 or later (GPLv3+)
Classifier: Operating System :: OS Independent
Classifier: Programming Language :: Python
Classifier: Programming Language :: Python :: 3
Classifier: Programming Language :: Python :: 3 :: Only
Classifier: Programming Language :: Python :: 3.6
Classifier: Programming Language :: Python :: 3.7
Classifier: Programming Language :: Python :: 3.8
Classifier: Programming Language :: Python :: 3.9
Classifier: Topic :: Multimedia
Classifier: Topic :: Utilities
Requires-Python: >=3.6
Provides-Extra: json
Provides-Extra: test
Provides-Extra: docs
License-File: LICENSE
License-File: COPYING.BSD
License-File: COPYING.GPL
